{
    "ohne_exo": {
        "exercise1" : [
            [57978, 87322]        
        ],
        "exercise2" : [
            [92434, 117739]
        ],
        "exercise3" : [
            [121198, 162271]
        ],
        "exercise4" : [
            [165407, 189058]
        ],
        "exercise5" : [
            [192194, 237305]
        ],
        "exercise6" : [
            [241516, 378052]
        ]
    },
    "mit_exo": {
        "exercise1" : [
            [70437, 99351]
        ],
        "exercise2" : [
            [104808, 128931]
        ],
        "exercise3" : [
            [132132, 183172]
        ],
        "exercise4" : [
            [187297, 205942]
        ],
        "exercise5" : [
            [210905, 250753]
        ],
        "exercise6" : [
            [254491, 390103]
        ]
    }
}