{
    "ohne_exo": {
        "exercise1" : [
            [64487, 127105]        
        ],
        "exercise2" : [
            [132068, 161003]
        ],
        "exercise3" : [
            [164311, 235888]
        ],
        "exercise4" : [
            [241902, 261429]
        ],
        "exercise5" : [
            [265296, 335841]
        ],
        "exercise6" : [
            [339815, 478908]
        ]
    },
    "mit_exo": {
        "exercise1" : [
            [69599, 114474]
        ],
        "exercise2" : [
            [117825, 150091]
        ],
        "exercise3" : [
            [153012, 206587]
        ],
        "exercise4" : [
            [211399, 229830]
        ],
        "exercise5" : [
            [232408, 278034]
        ],
        "exercise6" : [
            [281965, 415108]
        ]
    }
}