{
    "ohne_exo": {
        "exercise1" : [
            [69112, 90830]        
        ],
        "exercise2" : [
            [96115, 129841]
        ],
        "exercise3" : [
            [135834, 176133]
        ],
        "exercise4" : [
            [182728, 212007]
        ],
        "exercise5" : [
            [218452, 271898]
        ],
        "exercise6" : [
            [374343, 513199]
        ]
    },
    "mit_exo": {
        "exercise1" : [
            [64408, 80261]
        ],
        "exercise2" : [
            [84622, 97747]
        ],
        "exercise3" : [
            [101399, 136865]
        ],
        "exercise4" : [
            [142708, 168078]
        ],
        "exercise5" : [
            [173255, 220492]
        ],
        "exercise6" : [
            [226872, 355203]
        ]
    }
}